example/check_license.py
example/example.py
license_tool/__init__.py
license_tool/_version.py
license_tool/cli.cpython-311-aarch64-linux-musl.so
license_tool/keygen.cpython-311-aarch64-linux-musl.so
license_tool/key/__init__.py
license_tool/key/signer.cpython-311-aarch64-linux-musl.so
license_tool/key/verifier.cpython-311-aarch64-linux-musl.so
license_tool_ias-0.2.2.dist-info/METADATA
license_tool_ias-0.2.2.dist-info/WHEEL
license_tool_ias-0.2.2.dist-info/entry_points.txt
license_tool_ias-0.2.2.dist-info/top_level.txt
license_tool_ias-0.2.2.dist-info/RECORD
