Metadata-Version: 2.4
Name: license-tool-ias
Version: 0.2.2
Summary: Example algo package with Cython-compiled submodules
Author: Your Name
Classifier: Programming Language :: Python :: 3
Classifier: Programming Language :: Cython
Classifier: Programming Language :: C
Requires-Python: >=3.11
Requires-Dist: cryptography==45.0.5
